magiceden/__init__.py
magiceden-0.1.2.dist-info/LICENSE
magiceden-0.1.2.dist-info/WHEEL
magiceden-0.1.2.dist-info/METADATA
magiceden-0.1.2.dist-info/RECORD
